cmoonvision/CmoonVision.py
cmoonvision/__init__.py
cmoonvision/cmoon_utils.py
cmoonvision/cmoonvision_example.py
cmoonvision-0.2.1.dist-info/METADATA
cmoonvision-0.2.1.dist-info/WHEEL
cmoonvision-0.2.1.dist-info/RECORD
