Metadata-Version: 2.1
Name: cmoonvision
Version: 0.2.1
Summary: CmoonVision based on YoloV8
License: AGPL-3.0
Author: cmoon
Author-email: cmoon@mail.ustc.edu.cn
Requires-Python: >=3.10,<4.0
Classifier: License :: OSI Approved :: GNU Affero General Public License v3
Classifier: Programming Language :: Python :: 3
Classifier: Programming Language :: Python :: 3.10
Classifier: Programming Language :: Python :: 3.11
Classifier: Programming Language :: Python :: 3.12
Requires-Dist: ultralytics (==8.2.8)
